{
  "display": {
    "icon": {
      "id": "stone"
    },
    "title": "",
    "description": "",
    "show_toast": false,
    "announce_to_chat": false,
    "hidden": true
  },
  "parent": "namespace:all/root",
  "criteria": {
    "": {
      "trigger": "minecraft:inventory_changed",
      "conditions": {
        "items": [
          {
            "components": {
              "minecraft:custom_data": {
                "species": "armor"
              }
            }
          }
        ]
      }
    }
  },
  "rewards": {
    "function": "namespace:main/advancement/system/pick_armor"
  }
}